miktikpy/__init__.py
miktikpy/api.py
miktikpy/miktikpy.py
miktikpy-0.0.3.dist-info/LICENSE
miktikpy-0.0.3.dist-info/METADATA
miktikpy-0.0.3.dist-info/WHEEL
miktikpy-0.0.3.dist-info/top_level.txt
miktikpy-0.0.3.dist-info/RECORD
