Metadata-Version: 2.1
Name: miktikpy
Version: 0.0.3
Summary: Python api client for mikrotik os7 rest api
Author-email: uberkie <uberkie85@gmail.com>
Project-URL: Homepage, https://github.com/uberkie/mikpy
Classifier: Programming Language :: Python :: 3
Classifier: License :: OSI Approved :: MIT License
Classifier: Operating System :: OS Independent
Requires-Python: >=3.7
License-File: LICENSE
